{
  "project_info": {
    "project_number": "712816805143",
    "project_id": "helpdeskmarcos-c4ff3",
    "storage_bucket": "helpdeskmarcos-c4ff3.appspot.com"
  },
  "client": [
    {
      "client_info": {
        "mobilesdk_app_id": "1:712816805143:android:5331f2c9e967324d2ba352",
        "android_client_info": {
          "package_name": "com.helpdeskmarcos"
        }
      },
      "oauth_client": [
        {
          "client_id": "712816805143-d6dhhf5qvqj4ad8saottu319c06jrl2p.apps.googleusercontent.com",
          "client_type": 1,
          "android_info": {
            "package_name": "com.helpdeskmarcos",
            "certificate_hash": "5e8f16062ea3cd2c4a0d547876baa6f38cabf625"
          }
        },
        {
          "client_id": "712816805143-rk8d5gj3v16hl3qlvc073mmiksv27egs.apps.googleusercontent.com",
          "client_type": 3
        }
      ],
      "api_key": [
        {
          "current_key": "AIzaSyAVw09h-H5U1M71n1KEqfiQCzzKxsWC7nk"
        }
      ],
      "services": {
        "appinvite_service": {
          "other_platform_oauth_client": [
            {
              "client_id": "712816805143-rk8d5gj3v16hl3qlvc073mmiksv27egs.apps.googleusercontent.com",
              "client_type": 3
            }
          ]
        }
      }
    }
  ],
  "configuration_version": "1"
}